pushswapv/__init__.py
pushswapv/psw.py
pushswapv-0.1.0.dist-info/METADATA
pushswapv-0.1.0.dist-info/WHEEL
pushswapv-0.1.0.dist-info/entry_points.txt
pushswapv-0.1.0.dist-info/RECORD
