Metadata-Version: 2.3
Name: pushswapv
Version: 0.1.0
Summary: a push swap visualizer
Author-email: Tom0427 <82128211+Tom-game-project@users.noreply.github.com>
Requires-Python: >=3.10
